quantumrand/__init__.py
quantumrand/cmd.py
quantumrand/dev.py
quantumrand-2.2.0.dist-info/LICENSE
quantumrand-2.2.0.dist-info/METADATA
quantumrand-2.2.0.dist-info/WHEEL
quantumrand-2.2.0.dist-info/top_level.txt
quantumrand-2.2.0.dist-info/zip-safe
quantumrand-2.2.0.dist-info/RECORD
