Metadata-Version: 2.1
Name: quantumrand
Version: 2.2.0
Summary: A Python interface to the ANU Quantum Random Numbers Server; Maintained fork of quantumrandom
Home-page: https://github.com/identex/quantumrand
Author: Jason Carpenter
Author-email: brad@identex.co
License: MIT
Keywords: quantum random number generator
Platform: UNKNOWN
Classifier: Development Status :: 5 - Production/Stable
Classifier: License :: OSI Approved :: MIT License
Classifier: Topic :: Scientific/Engineering :: Mathematics
Classifier: Programming Language :: Python :: 3
Requires-Python: >=3.2
License-File: LICENSE
Requires-Dist: six
Requires-Dist: requests
